pycronscript/__init__.py
pycronscript/config.py
pycronscript/main.py
pycronscript-0.9.4.dist-info/LICENSE
pycronscript-0.9.4.dist-info/METADATA
pycronscript-0.9.4.dist-info/WHEEL
pycronscript-0.9.4.dist-info/entry_points.txt
pycronscript-0.9.4.dist-info/top_level.txt
pycronscript-0.9.4.dist-info/RECORD
