Metadata-Version: 2.1
Name: pycronscript
Version: 0.9.4
Summary: Schedule your Python scripts
Home-page: https://github.com/tiyujopite/pycronscript
Download-URL: https://github.com/tiyujopite/pycronscript
Author: José Antonio Díaz Miralles
Author-email: joseantoniodiazmiralles@gmail.com
License: MIT
Keywords: schedule,cron,python,scripts,tasks
Classifier: Development Status :: 4 - Beta
Classifier: Environment :: Plugins
Classifier: Intended Audience :: Developers
Classifier: Intended Audience :: System Administrators
Classifier: Operating System :: OS Independent
Classifier: Natural Language :: English
Classifier: License :: OSI Approved :: MIT License
Classifier: Programming Language :: Python :: 3.7
Classifier: Programming Language :: Python :: 3.8
Classifier: Programming Language :: Python :: 3.9
Classifier: Programming Language :: Python :: 3.10
Classifier: Programming Language :: Python :: 3.11
Classifier: Topic :: Software Development
Requires-Python: >=3.7
License-File: LICENSE
Requires-Dist: appdirs
